Workbook

Sheet Analysis
O1: Year | P1: Revenue | R1: Year | S1: EBIT margin | U1: Year | V1: Operating cash flow (€m) | W1: Simplified FCF (€m)
O2: 2021 | P2: ='Source Data'!C2/1000 -> 608.271 | R2: 2021 | S2: =Calculations!C3 -> 0.082196916 | U2: 2021 | V2: ='Source Data'!C4/1000 -> 102.429 | W2: =Calculations!C4/1000 -> 77.573
O3: 2022 | P3: ='Source Data'!D2/1000 -> 755.123 | R3: 2022 | S3: =Calculations!D3 -> 0.061681342 | U3: 2022 | V3: ='Source Data'!D4/1000 -> -17.945 | W3: =Calculations!D4/1000 -> -59.862
O4: 2023 | P4: ='Source Data'!E2/1000 -> 821.8 | R4: 2023 | S4: =Calculations!E3 -> 0.057377707 | U4: 2023 | V4: ='Source Data'!E4/1000 -> 30.391 | W4: =Calculations!E4/1000 -> -5.501
O5: 2024 | P5: ='Source Data'!F2/1000 -> 750.427 | R5: 2024 | S5: =Calculations!F3 -> 0.048978781 | U5: 2024 | V5: ='Source Data'!F4/1000 -> 85.001 | W5: =Calculations!F4/1000 -> 63.41
O6: 2025 | P6: ='Source Data'!G2/1000 -> 749.874 | R6: 2025 | S6: =Calculations!G3 -> 0.05551866 | U6: 2025 | V6: ='Source Data'!G4/1000 -> 23.276 | W6: =Calculations!G4/1000 -> 0.598
A27: Metric | B27: 2021 | C27: 2022 | D27: 2023 | E27: 2024 | F27: 2025
A28: Net debt (€m) | B28: =Calculations!C6/1000 -> -66.104 | C28: =Calculations!D6/1000 -> 22.837 | D28: =Calculations!E6/1000 -> 45.451 | E28: =Calculations!F6/1000 -> 3.341 | F28: =Calculations!G6/1000 -> 20.549
A29: Net gearing | B29: =Calculations!C7 -> -0.22237248 | C29: =Calculations!D7 -> 0.070963572 | D29: =Calculations!E7 -> 0.14124034 | E29: =Calculations!F7 -> 0.010211099 | F29: =Calculations!G7 -> 0.060761163
A30: Inventory / Revenue | B30: =Calculations!C9 -> 0.2752293 | C30: =Calculations!D9 -> 0.30411999 | D30: =Calculations!E9 -> 0.29306036 | E30: =Calculations!F9 -> 0.29199776 | F30: =Calculations!G9 -> 0.32007911
A31: Current debt / Total debt | B31: =Calculations!C10 -> 0.090243813 | C31: =Calculations!D10 -> 0.55878199 | D31: =Calculations!E10 -> 0.44214879 | E31: =Calculations!F10 -> 0.26477321 | F31: =Calculations!G10 -> 0.2220768
A33: KEY FINDINGS
A35: Question 1 | B35: What drove growth in 2023 (highest revenue between 2021-2025)
A41: Question 2 | B41: Why did revenue and EBIT decline in 2024
A47: Question 3 | B47: Why did profitability improve in 2025 while revenue stayed almost flat, but operating cash flow fell sharply
A53: Question 4 | B53: How did Ponsse’s balance-sheet and cash position change over 2021–2025

Sheet Source Data
A1: Metric | B1: Unit | C1: 2021 | D1: 2022 | E1: 2023 | F1: 2024 | G1: 2025 | I1: Notes
A2: Revenue | B2: €000 | C2: 608271 | D2: 755123 | E2: 821800 | F2: 750427 | G2: 749874 | I2: 2021 continuing-operations comparative from 2022 report. Russian discontinued operations excluded.
A3: EBIT | B3: €000 | C3: 49998 | D3: 46577 | E3: 47153 | F3: 36755 | G3: 41632 | I3: Russia removed from 2021 and 2022
A4: Operating Cash Flow | B4: €000 | C4: 102429 | D4: -17945 | E4: 30391 | F4: 85001 | G4: 23276
A5: Capital Expenditure | B5: €000 | C5: -24856 | D5: -41917 | E5: -35892 | F5: -21591 | G5: -22678
A6: Inventories | B6: €000 | C6: 167414 | D6: 229648 | E6: 240837 | F6: 219123 | G6: 240019
A7: Cash & cash equivalents | B7: €000 | C7: 120900 | D7: 73451 | E7: 74002 | F7: 83590 | G7: 58149
A8: Non-current interest-bearing liabilities | B8: €000 | C8: 49851 | D8: 42484 | E8: 66637 | F8: 63914 | G8: 61221
A9: Current interest-bearing liabilities | B9: €000 | C9: 4945 | D9: 53804 | E9: 52816 | F9: 23017 | G9: 17477
A10: Equity | B10: €000 | C10: 297267 | D10: 321813 | E10: 321799 | F10: 327193 | G10: 338193

Sheet Calculations
A1: Metric | B1: Unit | C1: 2021 | D1: 2022 | E1: 2023 | F1: 2024 | G1: 2025
A2: Revenue growth | B2: % | D2: ='Source Data'!D2/'Source Data'!C2-1 -> 0.24142529 | E2: ='Source Data'!E2/'Source Data'!D2-1 -> 0.088299522 | F2: ='Source Data'!F2/'Source Data'!E2-1 -> -0.086849598 | G2: ='Source Data'!G2/'Source Data'!F2-1 -> -0.00073691378
A3: EBIT margin | B3: % | C3: ='Source Data'!C3/'Source Data'!C2 -> 0.082196916 | D3: ='Source Data'!D3/'Source Data'!D2 -> 0.061681342 | E3: ='Source Data'!E3/'Source Data'!E2 -> 0.057377707 | F3: ='Source Data'!F3/'Source Data'!F2 -> 0.048978781 | G3: ='Source Data'!G3/'Source Data'!G2 -> 0.05551866
A4: Free cash flow | B4: €000 | C4: ='Source Data'!C4+'Source Data'!C5 -> 77573 | D4: ='Source Data'!D4+'Source Data'!D5 -> -59862 | E4: ='Source Data'!E4+'Source Data'!E5 -> -5501 | F4: ='Source Data'!F4+'Source Data'!F5 -> 63410 | G4: ='Source Data'!G4+'Source Data'!G5 -> 598
A5: Total debt | B5: €000 | C5: ='Source Data'!C8+'Source Data'!C9 -> 54796 | D5: ='Source Data'!D8+'Source Data'!D9 -> 96288 | E5: ='Source Data'!E8+'Source Data'!E9 -> 119453 | F5: ='Source Data'!F8+'Source Data'!F9 -> 86931 | G5: ='Source Data'!G8+'Source Data'!G9 -> 78698
A6: Net debt | B6: €000 | C6: =C5-'Source Data'!C7 -> -66104 | D6: =D5-'Source Data'!D7 -> 22837 | E6: =E5-'Source Data'!E7 -> 45451 | F6: =F5-'Source Data'!F7 -> 3341 | G6: =G5-'Source Data'!G7 -> 20549
A7: Net gearing | B7: % | C7: =C6/'Source Data'!C10 -> -0.22237248 | D7: =D6/'Source Data'!D10 -> 0.070963572 | E7: =E6/'Source Data'!E10 -> 0.14124034 | F7: =F6/'Source Data'!F10 -> 0.010211099 | G7: =G6/'Source Data'!G10 -> 0.060761163
A8: CapEx / Revenue | B8: % | C8: =ABS('Source Data'!C5)/'Source Data'!C2 -> 0.040863365 | D8: =ABS('Source Data'!D5)/'Source Data'!D2 -> 0.055510162 | E8: =ABS('Source Data'!E5)/'Source Data'!E2 -> 0.04367486 | F8: =ABS('Source Data'!F5)/'Source Data'!F2 -> 0.028771619 | G8: =ABS('Source Data'!G5)/'Source Data'!G2 -> 0.030242414
A9: Inventory / Revenue | B9: % | C9: ='Source Data'!C6/'Source Data'!C2 -> 0.2752293 | D9: ='Source Data'!D6/'Source Data'!D2 -> 0.30411999 | E9: ='Source Data'!E6/'Source Data'!E2 -> 0.29306036 | F9: ='Source Data'!F6/'Source Data'!F2 -> 0.29199776 | G9: ='Source Data'!G6/'Source Data'!G2 -> 0.32007911
A10: Current / Total Debt | B10: % | C10: ='Source Data'!C9/C5 -> 0.090243813 | D10: ='Source Data'!D9/D5 -> 0.55878199 | E10: ='Source Data'!E9/E5 -> 0.44214879 | F10: ='Source Data'!F9/F5 -> 0.26477321 | G10: ='Source Data'!G9/G5 -> 0.2220768
A12: Metric | B12: Unit | C12: Result
A13: Revenue CAGR 2021-2025 | B13: % | C13: =('Source Data'!G2/'Source Data'!C2)^(1/4)-1 -> 0.053714111

Sheet Sources
A1: Year | B1: Report | C1: Statement | D1: Page | E1: Figures Used | F1: Notes
A2: 2021 | B2: Ponsse Annual Report 2022 | C2: Statement of comprehensive income | D2: 51 | E2: Revenue, EBIT | F2: 2021 restated to continuing operations. Russian discontinued operations excluded
A3: 2021 | B3: Ponsse Annual Report 2021 | C3: Cash flow statement | D3: 72 | E3: OCF, CapEx
A4: 2021 | B4: Ponsse Annual Report 2021 | C4: Statement of financial position | D4: 71 | E4: Inventory, cash, debt, equity
A5: 2022 | B5: Ponsse Annual Report 2022 | C5: Statement of comprehensive income | D5: 51 | E5: Revenue, EBIT
A6: 2022 | B6: Ponsse Annual Report 2022 | C6: Cash flow statement | D6: 53 | E6: OCF, CapEx
A7: 2022 | B7: Ponsse Annual Report 2022 | C7: Statement of financial position | D7: 52 | E7: Inventory, cash, debt, equity
A8: 2022 | B8: Ponsse Annual Report 2023 | C8: Statement of changes in equity | D8: 66 | E8: Corrected opening 2023 equity | F8: 2022 year-end equity originally 321,813. Corrected opening 2023 equity 316,851
A9: 2023 | B9: Ponsse Annual Report 2023 | C9: Statement of comprehensive income | D9: 63 | E9: Revenue, EBIT
A10: 2023 | B10: Ponsse Annual Report 2023 | C10: Cash flow statement | D10: 65 | E10: OCF, CapEx
A11: 2023 | B11: Ponsse Annual Report 2023 | C11: Statement of financial position | D11: 64 | E11: Inventory, cash, debt, equity
A12: 2024 | B12: Ponsse Annual Report 2024 | C12: Statement of comprehensive income | D12: 111 | E12: Revenue, EBIT
A13: 2024 | B13: Ponsse Annual Report 2024 | C13: Cash flow statement | D13: 113 | E13: OCF, CapEx
A14: 2024 | B14: Ponsse Annual Report 2024 | C14: Statement of financial position | D14: 112 | E14: Inventory, cash, debt, equity
A15: 2025 | B15: Ponsse Annual Report 2025 | C15: Statement of comprehensive income | D15: 120 | E15: Revenue, EBIT
A16: 2025 | B16: Ponsse Annual Report 2025 | C16: Cash flow statement | D16: 122 | E16: OCF, CapEx
A17: 2025 | B17: Ponsse Annual Report 2025 | C17: Statement of financial position | D17: 121 | E17: Inventory, cash, debt, equity
